{"version":"3.30","pathname":"S/SM/SMUELLER/ExtUtils-ParseXS-3.30.tar.gz","target":"ExtUtils::ParseXS","provides":{"ExtUtils::Typemaps::OutputMap":{"version":"3.30","file":"lib/ExtUtils/Typemaps/OutputMap.pm"},"ExtUtils::Typemaps":{"file":"lib/ExtUtils/Typemaps.pm","version":"3.30"},"ExtUtils::ParseXS::CountLines":{"version":"3.30","file":"lib/ExtUtils/ParseXS/CountLines.pm"},"ExtUtils::ParseXS::Constants":{"file":"lib/ExtUtils/ParseXS/Constants.pm","version":"3.30"},"ExtUtils::ParseXS::Eval":{"version":"3.30","file":"lib/ExtUtils/ParseXS/Eval.pm"},"ExtUtils::Typemaps::Cmd":{"version":"3.30","file":"lib/ExtUtils/Typemaps/Cmd.pm"},"ExtUtils::Typemaps::Type":{"version":"3.30","file":"lib/ExtUtils/Typemaps/Type.pm"},"ExtUtils::ParseXS::Utilities":{"version":"3.30","file":"lib/ExtUtils/ParseXS/Utilities.pm"},"ExtUtils::ParseXS":{"version":"3.30","file":"lib/ExtUtils/ParseXS.pm"},"ExtUtils::Typemaps::InputMap":{"file":"lib/ExtUtils/Typemaps/InputMap.pm","version":"3.30"}},"dist":"ExtUtils-ParseXS-3.30","name":"ExtUtils::ParseXS"}